{
  "generatedAt": "2026-07-22T09:32:37.849788+00:00",
  "count": 12,
  "cards": [
    {
      "region": "중동",
      "title": "[사설] 확산되는 중동 갈등, 홍해 봉쇄에도 대비해야",
      "link": "https://www.hani.co.kr/arti/opinion/editorial/1269490.html",
      "pubDate": "Wed, 22 Jul 2026 18:28:00 +0900",
      "sev": "lo",
      "global": "호르무즈해협을 둘러싼 미국-이란 전쟁의 불씨가 유럽과 아시아를 잇는 세계 물류의 ‘대동맥’인 홍해에까지 옮겨붙었다. 이란의 지원을 받는 예멘의 후티 반군이 숙적인",
      "korea": "(생성 실패 - 원문 참고)",
      "exchange": "(생성 실패 - 원문 참고)"
    },
    {
      "region": "중동",
      "title": "호르무즈·홍해 이어 흑해까지 다 막히나…전 세계 ‘기름줄’ 전쟁에 ...",
      "link": "https://nownews.seoul.co.kr/news/newsView.php?id=20260722601021&wlog_tag3=naver",
      "pubDate": "Wed, 22 Jul 2026 18:26:00 +0900",
      "sev": "lo",
      "global": "앞서 사우디는 이란의 호르무즈 해협 봉쇄에 대비해 막대한 예산을 들여 아라비아반도를 가로지르는 대체 송유관을 구축했다. 이를 통해 원유를 운송한 후 홍해의 주요 ",
      "korea": "(생성 실패 - 원문 참고)",
      "exchange": "(생성 실패 - 원문 참고)"
    },
    {
      "region": "중동",
      "title": "[뭔데이 메탈] 칠레도 BHP도 생산 감소... 구리 공급망 '경고등'",
      "link": "https://www.meconomynews.com/news/articleView.html?idxno=132933",
      "pubDate": "Wed, 22 Jul 2026 18:20:00 +0900",
      "sev": "lo",
      "global": "NH선물은 17일 발간한 보고서에서 미국과 이란의 무력 충돌이 이어지면서 호르무즈 해협 물류 차질 우려가 커졌고, 국제 유가가 한 주 동안 13.2% 급등했다고 ",
      "korea": "(생성 실패 - 원문 참고)",
      "exchange": "(생성 실패 - 원문 참고)"
    },
    {
      "region": "중동",
      "title": "\"홍해 봉쇄땐 세계 원유공급 25% 타격\"",
      "link": "http://www.fnnews.com/news/202607221816513033",
      "pubDate": "Wed, 22 Jul 2026 18:18:00 +0900",
      "sev": "lo",
      "global": "미국과 이란 전쟁이 격화되면서 세계 에너지 공급 리스크도 커지고 있다. 사우디아라비아를 겨냥한 예멘... 월스트리트저널(WSJ) 등은 22일(현지시간) 주요 원유",
      "korea": "(생성 실패 - 원문 참고)",
      "exchange": "(생성 실패 - 원문 참고)"
    },
    {
      "region": "중동",
      "title": "홍해 입구 유조선 회항 속출…“원유 공급 25% 타격 가능”",
      "link": "https://news.kbs.co.kr/news/pc/view/view.do?ncd=8617289&ref=A",
      "pubDate": "Wed, 22 Jul 2026 18:09:00 +0900",
      "sev": "lo",
      "global": "친이란 예멘 후티 반군이 사우디 해상 봉쇄를 선언한 뒤 우회로를 선택한 선박들이 속속 생겨나고 있습니다. 호르무즈 해협을 비롯해 홍해까지 봉쇄 수순을 밟으면서 세",
      "korea": "(생성 실패 - 원문 참고)",
      "exchange": "(생성 실패 - 원문 참고)"
    },
    {
      "region": "중동",
      "title": "[외환-마감] 중동 리스크에 7거래일만 상승…6.70원↑",
      "link": "https://news.einfomax.co.kr/news/articleView.html?idxno=4426270",
      "pubDate": "Wed, 22 Jul 2026 18:06:00 +0900",
      "sev": "lo",
      "global": "마코 루비오 미국 국무장관은 이날 필리핀에서 열린 아세안 외교장관회의에서 이란이 호르무즈 해협을 장악할 경우 중동을 넘어서까지 파장을 미칠 위험한 선례가 될 것이",
      "korea": "(생성 실패 - 원문 참고)",
      "exchange": "(생성 실패 - 원문 참고)"
    },
    {
      "region": "중동",
      "title": "[특임공관장 시대③] 맞춤형 '실용외교' 선봉에… 재외국민 안전도 책임",
      "link": "https://www.ajunews.com/view/20260722153805505",
      "pubDate": "Wed, 22 Jul 2026 18:22:00 +0900",
      "sev": "lo",
      "global": "대상 공관은 △주사우디아라비아대사관 △주이스라엘 대사관 △주이라크대사관 △주레바논대사관 △주쿠웨이트대사관 △주바레인대사관 △주아랍에미리트(UAE)대사관 △주두바이",
      "korea": "(생성 실패 - 원문 참고)",
      "exchange": "(생성 실패 - 원문 참고)"
    },
    {
      "region": "중동",
      "title": "‘천조국’의 충격적인 현실…“미군, 돈 없어서 훈련도 못해” 실태 공...",
      "link": "https://nownews.seoul.co.kr/news/newsView.php?id=20260722601018&wlog_tag3=naver",
      "pubDate": "Wed, 22 Jul 2026 17:51:00 +0900",
      "sev": "lo",
      "global": "트럼프 대통령은 이날 백악관에서 조셉 아운 레바논 대통령과의 회담 중 후티 반군의 홍해 항로 봉쇄... 월스트리트저널은 “곡괭이 산은 수년간 미국과 이스라엘의 감",
      "korea": "(생성 실패 - 원문 참고)",
      "exchange": "(생성 실패 - 원문 참고)"
    },
    {
      "region": "중동",
      "title": "트럼프 “이란 핵시설 곧 타격”… 이란 “전쟁 확대 행위로 간주” 반...",
      "link": "https://www.hankookilbo.com/news/article/A2026072209500004305?did=NA",
      "pubDate": "Wed, 22 Jul 2026 17:22:00 +0900",
      "sev": "lo",
      "global": "트럼프 대통령은 21일(현지시간) 워싱턴의 백악관에서 열린 조셉 아운 레바논 대통령과의 회담 자리에서... 월스트리트저널(WSJ)에 따르면 이스라엘 정보당국은 지",
      "korea": "(생성 실패 - 원문 참고)",
      "exchange": "(생성 실패 - 원문 참고)"
    },
    {
      "region": "중동",
      "title": "美 이란 재공습에도 이스라엘 개입 자제 압박…\"통제 불능 우려\"",
      "link": "https://www.newsis.com/view/NISX20260722_0003718721",
      "pubDate": "Wed, 22 Jul 2026 15:45:00 +0900",
      "sev": "lo",
      "global": "도널드 트럼프 미국 대통령은 베냐민 네타냐후 이스라엘 총리의 확전 성향이 가자지구와 레바논, 이란에서 전투를 끝내려는 자신의 노력을 어렵게 만들었다고 불평해 왔다",
      "korea": "(생성 실패 - 원문 참고)",
      "exchange": "(생성 실패 - 원문 참고)"
    },
    {
      "region": "중동",
      "title": "美·이란 충돌 격화에 홍해 봉쇄 우려까지…국제유가 상승",
      "link": "https://www.industrynews.co.kr/news/articleView.html?idxno=83555",
      "pubDate": "Wed, 22 Jul 2026 15:14:00 +0900",
      "sev": "lo",
      "global": "로이터·블룸버그 통신 등에 따르면, 도널드 트럼프 미국 대통령은 이날 백악관에서 조셉 아운 레바논... 그는 미국과 이스라엘이 이란의 비밀 핵시설로 의심하는 이른",
      "korea": "(생성 실패 - 원문 참고)",
      "exchange": "(생성 실패 - 원문 참고)"
    },
    {
      "region": "중동",
      "title": "트럼프 “홍해 봉쇄 시 처리할 것...이란 곡괭이산 곧 타격”",
      "link": "https://www.seoul.co.kr/news/international/2026/07/22/20260722500212?wlog_tag3=naver",
      "pubDate": "Wed, 22 Jul 2026 15:00:00 +0900",
      "sev": "lo",
      "global": "레바논 대통령과 회담에서 후티 반군 대응 방안 언급 美, 이란과 전쟁 비용 55조원...“미사일 부족” 보도도... 미국과 이스라엘은 이란이 지난 2020년부터 ",
      "korea": "(생성 실패 - 원문 참고)",
      "exchange": "(생성 실패 - 원문 참고)"
    }
  ]
}